lazy_ci/__about__.py
lazy_ci/code_quality.py
lazy_ci/main.py
lazy_ci/ship.py
lazy_ci/test/test_ship.py
lazy_ci-1.0.5.dist-info/METADATA
lazy_ci-1.0.5.dist-info/WHEEL
lazy_ci-1.0.5.dist-info/entry_points.txt
lazy_ci-1.0.5.dist-info/licenses/LICENSE
lazy_ci-1.0.5.dist-info/RECORD
